duckboat/__init__.py
duckboat/database.py
duckboat/mixin_database.py
duckboat/mixin_do.py
duckboat/mixin_table.py
duckboat/table.py
duckboat/ddb/__init__.py
duckboat/ddb/_con.py
duckboat/ddb/_query.py
duckboat/ddb/_relation.py
duckboat-0.17.0.dist-info/METADATA
duckboat-0.17.0.dist-info/WHEEL
duckboat-0.17.0.dist-info/licenses/LICENSE
duckboat-0.17.0.dist-info/RECORD
