Metadata-Version: 2.4
Name: duckboat
Version: 0.17.0
Summary: A SQL-based Python dataframe library for ergonomic interactive data analysis and exploration.
Project-URL: homepage, https://github.com/ajfriend/duckboat
Project-URL: repository, https://github.com/ajfriend/duckboat
Project-URL: documentation, https://ajfriend.github.io/duckboat
Project-URL: pypi, https://pypi.org/project/duckboat
Author-email: AJ Friend <ajfriend@gmail.com>
License: BSD 3-Clause License
License-File: LICENSE
Keywords: ETL,SQL,data-wrangling,duckdb,pipelines
Requires-Python: >=3.9
Requires-Dist: duckdb
Requires-Dist: pandas
Requires-Dist: pyarrow
Provides-Extra: all
Requires-Dist: ipykernel; extra == 'all'
Requires-Dist: jupyterlab; extra == 'all'
Requires-Dist: jupyterlab-execute-time; extra == 'all'
Requires-Dist: matplotlib; extra == 'all'
Requires-Dist: polars; extra == 'all'
Requires-Dist: pytest; extra == 'all'
Requires-Dist: pytest-cov; extra == 'all'
Requires-Dist: ruff; extra == 'all'
Provides-Extra: dev
Requires-Dist: ipykernel; extra == 'dev'
Requires-Dist: jupyterlab; extra == 'dev'
Requires-Dist: jupyterlab-execute-time; extra == 'dev'
Provides-Extra: docs
Requires-Dist: matplotlib; extra == 'docs'
Provides-Extra: test
Requires-Dist: pytest; extra == 'test'
Requires-Dist: pytest-cov; extra == 'test'
Requires-Dist: ruff; extra == 'test'
